LICENSE
MANIFEST.in
README.rst
setup.cfg
setup.py
docs/Makefile
docs/Notes.md
docs/api.rst
docs/conf.py
docs/index.rst
docs/internals.rst
docs/make.bat
pybufrkit/__init__.py
pybufrkit/__main__.py
pybufrkit/bitops.py
pybufrkit/bufr.py
pybufrkit/coder.py
pybufrkit/commands.py
pybufrkit/constants.py
pybufrkit/dataprocessor.py
pybufrkit/dataquery.py
pybufrkit/decoder.py
pybufrkit/descriptors.py
pybufrkit/encoder.py
pybufrkit/errors.py
pybufrkit/mdquery.py
pybufrkit/query.py
pybufrkit/renderer.py
pybufrkit/script.py
pybufrkit/tables.py
pybufrkit/tablespreparer.py
pybufrkit/templatecompiler.py
pybufrkit/templatedata.py
pybufrkit/utils.py
pybufrkit.egg-info/PKG-INFO
pybufrkit.egg-info/SOURCES.txt
pybufrkit.egg-info/dependency_links.txt
pybufrkit.egg-info/entry_points.txt
pybufrkit.egg-info/requires.txt
pybufrkit.egg-info/top_level.txt
pybufrkit/definitions/section0.json
pybufrkit/definitions/section1-1.json
pybufrkit/definitions/section1-2.json
pybufrkit/definitions/section1-3.json
pybufrkit/definitions/section1-4.json
pybufrkit/definitions/section2.json
pybufrkit/definitions/section3.json
pybufrkit/definitions/section4.json
pybufrkit/definitions/section5.json
pybufrkit/tables/0/0_0/10/TableB.json
pybufrkit/tables/0/0_0/10/TableD.json
pybufrkit/tables/0/0_0/10/code_and_flag.json
pybufrkit/tables/0/0_0/11/TableB.json
pybufrkit/tables/0/0_0/11/TableD.json
pybufrkit/tables/0/0_0/11/code_and_flag.json
pybufrkit/tables/0/0_0/12/TableB.json
pybufrkit/tables/0/0_0/12/TableD.json
pybufrkit/tables/0/0_0/12/code_and_flag.json
pybufrkit/tables/0/0_0/13/TableB.json
pybufrkit/tables/0/0_0/13/TableD.json
pybufrkit/tables/0/0_0/13/code_and_flag.json
pybufrkit/tables/0/0_0/14/TableB.json
pybufrkit/tables/0/0_0/14/TableD.json
pybufrkit/tables/0/0_0/14/code_and_flag.json
pybufrkit/tables/0/0_0/15/TableB.json
pybufrkit/tables/0/0_0/15/TableD.json
pybufrkit/tables/0/0_0/15/code_and_flag.json
pybufrkit/tables/0/0_0/16/TableB.json
pybufrkit/tables/0/0_0/16/TableD.json
pybufrkit/tables/0/0_0/16/code_and_flag.json
pybufrkit/tables/0/0_0/17/TableB.json
pybufrkit/tables/0/0_0/17/TableD.json
pybufrkit/tables/0/0_0/17/code_and_flag.json
pybufrkit/tables/0/0_0/18/TableB.json
